nextcode/__init__.py
nextcode/client.py
nextcode/config.py
nextcode/credentials.py
nextcode/csa.py
nextcode/exceptions.py
nextcode/keycloak.py
nextcode/nextcode.py
nextcode/packagelocal.py
nextcode/services/__init__.py
nextcode/services/phenoteke/__init__.py
nextcode/services/phenoteke/service.py
nextcode/services/phenotype/__init__.py
nextcode/services/phenotype/analysis_catalog.py
nextcode/services/phenotype/analysis_catalog_run.py
nextcode/services/phenotype/exceptions.py
nextcode/services/phenotype/phenotype.py
nextcode/services/phenotype/phenotype_matrix.py
nextcode/services/phenotype/playlist.py
nextcode/services/phenotype/service.py
nextcode/services/pipelines/__init__.py
nextcode/services/pipelines/exceptions.py
nextcode/services/pipelines/job.py
nextcode/services/pipelines/service.py
nextcode/services/project/__init__.py
nextcode/services/project/exceptions.py
nextcode/services/project/service.py
nextcode/services/query/__init__.py
nextcode/services/query/exceptions.py
nextcode/services/query/jupyter.py
nextcode/services/query/query.py
nextcode/services/query/service.py
nextcode/services/query/utils.py
nextcode/services/queryserver/__init__.py
nextcode/services/queryserver/result.py
nextcode/services/queryserver/service.py
nextcode/services/workflow/__init__.py
nextcode/services/workflow/exceptions.py
nextcode/services/workflow/job.py
nextcode/services/workflow/pytest_plugin.py
nextcode/services/workflow/service.py
nextcode/services/workflow/weblog.py
nextcode/session.py
nextcode/utils.py
nextcode_sdk-2.1.2.dist-info/LICENSE
nextcode_sdk-2.1.2.dist-info/METADATA
nextcode_sdk-2.1.2.dist-info/WHEEL
nextcode_sdk-2.1.2.dist-info/RECORD
