Metadata-Version: 2.1
Name: nextcode-sdk
Version: 2.1.2
Summary: Python SDK for Genuity Science Services
Home-page: https://www.github.com/wuxi-nextcode/nextcode-python-sdk
License: MIT
Author: WUXI NextCODE
Author-email: support@wuxinextcode.com
Maintainer: Genuity Science Software Development
Maintainer-email: sdev@genuitysci.com
Requires-Python: >=3.9,<4.0
Classifier: Development Status :: 3 - Alpha
Classifier: Environment :: Web Environment
Classifier: Framework :: Jupyter
Classifier: Intended Audience :: Developers
Classifier: License :: OSI Approved :: MIT License
Classifier: Operating System :: OS Independent
Classifier: Programming Language :: Python :: 3
Classifier: Programming Language :: Python :: 3.9
Classifier: Programming Language :: Python :: 3.10
Classifier: Programming Language :: Python :: 3.11
Classifier: Programming Language :: Python :: 3.12
Classifier: Programming Language :: Python :: 3.13
Classifier: Programming Language :: Python :: 3.6
Classifier: Programming Language :: Python :: 3.7
Classifier: Programming Language :: Python :: 3.8
Classifier: Topic :: Internet :: WWW/HTTP
Classifier: Topic :: Internet :: WWW/HTTP :: Dynamic Content
Classifier: Topic :: Software Development :: Libraries :: Application Frameworks
Classifier: Topic :: Software Development :: Libraries :: Python Modules
Provides-Extra: jupyter
Requires-Dist: PyJWT (>=2.6.0,<3.0.0)
Requires-Dist: PyYAML (>=6.0,<7.0)
Requires-Dist: boto3 (>=1.26.125,<2.0.0)
Requires-Dist: hjson (>=3.1.0,<4.0.0)
Requires-Dist: ipython (>=8.13.1,<9.0.0) ; extra == "jupyter"
Requires-Dist: ipywidgets (>=8.0.6,<9.0.0) ; extra == "jupyter"
Requires-Dist: pandas (>=2.0.1,<3.0.0) ; extra == "jupyter"
Requires-Dist: plotly (>=5.14.1,<6.0.0) ; extra == "jupyter"
Requires-Dist: python-dateutil (>=2.8.2,<3.0.0)
Requires-Dist: requests (>=2.29.0,<3.0.0)
Requires-Dist: termcolor (>=2.3.0,<3.0.0) ; extra == "jupyter"
Requires-Dist: tqdm (>=4.65.0,<5.0.0) ; extra == "jupyter"
Project-URL: Documentation, https://wuxi-nextcode.github.io/nextcode-python-sdk/
Project-URL: Repository, https://www.github.com/wuxi-nextcode/nextcode-python-sdk
